slackfm/__init__.py
slackfm/__main__.py
slackfm/args.py
slackfm/commands.py
slackfm/constants.py
slackfm/log.py
slackfm/slack.py
slackfm/spotify.py
slackfm/utils.py
slackfm-0.1.0.dist-info/licenses/LICENSE
slackfm-0.1.0.dist-info/METADATA
slackfm-0.1.0.dist-info/WHEEL
slackfm-0.1.0.dist-info/entry_points.txt
slackfm-0.1.0.dist-info/top_level.txt
slackfm-0.1.0.dist-info/RECORD
